MANIFEST.in
README.rst
agpl-3.0.txt
arvados-node-manager.service
arvados_version.py
setup.py
arvados_node_manager.egg-info/PKG-INFO
arvados_node_manager.egg-info/SOURCES.txt
arvados_node_manager.egg-info/dependency_links.txt
arvados_node_manager.egg-info/not-zip-safe
arvados_node_manager.egg-info/requires.txt
arvados_node_manager.egg-info/top_level.txt
arvnodeman/__init__.py
arvnodeman/_version.py
arvnodeman/baseactor.py
arvnodeman/clientactor.py
arvnodeman/config.py
arvnodeman/daemon.py
arvnodeman/jobqueue.py
arvnodeman/launcher.py
arvnodeman/nodelist.py
arvnodeman/status.py
arvnodeman/timedcallback.py
arvnodeman/computenode/__init__.py
arvnodeman/computenode/dispatch/__init__.py
arvnodeman/computenode/dispatch/slurm.py
arvnodeman/computenode/dispatch/transitions.py
arvnodeman/computenode/driver/__init__.py
arvnodeman/computenode/driver/azure.py
arvnodeman/computenode/driver/dummy.py
arvnodeman/computenode/driver/ec2.py
arvnodeman/computenode/driver/gce.py
arvnodeman/test/__init__.py
arvnodeman/test/fake_driver.py
bin/arvados-node-manager
tests/__init__.py
tests/integration_test.py
tests/test_arguments.py
tests/test_clientactor.py
tests/test_computenode.py
tests/test_computenode_dispatch.py
tests/test_computenode_dispatch_slurm.py
tests/test_computenode_driver.py
tests/test_computenode_driver_azure.py
tests/test_computenode_driver_ec2.py
tests/test_computenode_driver_gce.py
tests/test_config.py
tests/test_daemon.py
tests/test_failure.py
tests/test_jobqueue.py
tests/test_nodelist.py
tests/test_status.py
tests/test_timedcallback.py
tests/testutil.py