Metadata-Version: 1.0
Name: arvados-node-manager
Version: 1.4.0
Summary: Arvados compute node manager
Home-page: https://arvados.org
Author: Arvados
Author-email: info@arvados.org
License: GNU Affero General Public License, version 3.0
Platform: UNKNOWN
